{
    "Ar36": {
        "error": 0.0003670531538920204,
        "error_type": "SEM",
        "filter_outliers_dict": {
            "filter_outliers": true,
            "iterations": 1,
            "std_devs": 2
        },
        "fit": "Linear",
        "value": 0.017575648314345334
    },
    "Ar37": {
        "error": 0.009337028739461288,
        "error_type": "SEM",
        "filter_outliers_dict": {
            "filter_outliers": true,
            "iterations": 1,
            "std_devs": 2
        },
        "fit": "linear",
        "value": -0.005359203342390467
    },
    "Ar38": {
        "error": 0.006027918901185585,
        "error_type": "SEM",
        "filter_outliers_dict": {
            "filter_outliers": true,
            "iterations": 1,
            "std_devs": 2
        },
        "fit": "linear",
        "value": 2.5256661210361875
    },
    "Ar39": {
        "error": 0.03270337640172166,
        "error_type": "SEM",
        "filter_outliers_dict": {
            "filter_outliers": true,
            "iterations": 1,
            "std_devs": 2
        },
        "fit": "Linear",
        "value": 204.86351130537074
    },
    "Ar40": {
        "error": 0.02509022749109768,
        "error_type": "SEM",
        "filter_outliers_dict": {
            "filter_outliers": true,
            "iterations": 1,
            "std_devs": 2
        },
        "fit": "Linear",
        "value": 200.67815451212408
    },
    "Ar41": {
        "error": 0.0021988104851998003,
        "error_type": "SEM",
        "filter_outliers_dict": {
            "filter_outliers": true,
            "iterations": 1,
            "std_devs": 2
        },
        "fit": "Average",
        "value": 0.008655047204104255
    }
}